ojmicroline_thermostat/__init__.py
ojmicroline_thermostat/const.py
ojmicroline_thermostat/exceptions.py
ojmicroline_thermostat/models/__init__.py
ojmicroline_thermostat/models/schedule.py
ojmicroline_thermostat/models/thermostat.py
ojmicroline_thermostat/ojmicroline.py
ojmicroline_thermostat/py.typed
ojmicroline_thermostat/wd5.py
ojmicroline_thermostat/wg4.py
ojmicroline_thermostat-3.3.0.dist-info/LICENSE
ojmicroline_thermostat-3.3.0.dist-info/METADATA
ojmicroline_thermostat-3.3.0.dist-info/WHEEL
ojmicroline_thermostat-3.3.0.dist-info/RECORD
