Metadata-Version: 2.3
Name: ojmicroline-thermostat
Version: 3.3.0
Summary: Asynchronous Python client controlling an OJ Microline Thermostat.
License: MIT
Keywords: async,client,thermostat,ojmicroline,thermostat
Author: Robbin Janssen
Author-email: robbinjanssen@gmail.com
Maintainer: Robbin Janssen
Maintainer-email: robbinjanssen@gmail.com
Requires-Python: >=3.11,<4.0
Classifier: Framework :: AsyncIO
Classifier: Intended Audience :: Developers
Classifier: License :: OSI Approved :: MIT License
Classifier: Natural Language :: English
Classifier: Programming Language :: Python :: 3
Classifier: Programming Language :: Python :: 3.11
Classifier: Programming Language :: Python :: 3.12
Classifier: Programming Language :: Python :: 3.13
Classifier: Topic :: Software Development :: Libraries :: Python Modules
Requires-Dist: aiohttp (>=3.0.0)
Requires-Dist: yarl (>=1.6.0)
Project-URL: Bug Tracker, https://github.com/robbinjanssen/python-ojmicroline-thermostat/issues
Project-URL: Changelog, https://github.com/robbinjanssen/python-ojmicroline-thermostat/releases
Project-URL: Documentation, https://github.com/robbinjanssen/python-ojmicroline-thermostat
Project-URL: Homepage, https://github.com/robbinjanssen/python-ojmicroline-thermostat
Project-URL: Repository, https://github.com/robbinjanssen/python-ojmicroline-thermostat
